pyjsonpath.py
pyjsonpath-1.2.3.dist-info/LICENSE
pyjsonpath-1.2.3.dist-info/METADATA
pyjsonpath-1.2.3.dist-info/WHEEL
pyjsonpath-1.2.3.dist-info/top_level.txt
pyjsonpath-1.2.3.dist-info/RECORD
