Metadata-Version: 2.1
Name: pyjsonpath
Version: 1.2.3
Summary: A Python toolkit for parsing JSON document
Home-page: https://github.com/hitplum/pyjsonpath
Author: hitplum
Author-email: ycx921101@163.com
License: MIT
Platform: UNKNOWN
Classifier: Programming Language :: Python :: 3.5
Classifier: Programming Language :: Python :: 3.6
Classifier: Programming Language :: Python :: 3.7
Classifier: Programming Language :: Python :: 3.8
Classifier: Programming Language :: Python :: 3.9
Classifier: Programming Language :: Python :: Implementation :: PyPy
Classifier: License :: OSI Approved :: MIT License
Requires-Python: >=3.5
